[ {
  "id" : "4d0c4a43-a3ec-d175-53ee-e0f10066a7b1",
  "name" : "icon",
  "display_width" : null,
  "label" : "Icon",
  "required" : false,
  "locked" : false,
  "responsive" : true,
  "resizable" : true,
  "show_loading" : false,
  "type" : "image",
  "default" : {
    "size_type" : "auto",
    "src" : "https://47980142.fs1.hubspotusercontent-na1.net/hubfs/47980142/placeholder-1024x1024.png",
    "alt" : "placeholder-1024x1024",
    "loading" : "lazy",
    "width" : 1024,
    "height" : 1024,
    "max_width" : 1024,
    "max_height" : 1024
  }
}, {
  "id" : "e8fe560c-e9f3-1ac0-a9c7-d2398019a650",
  "name" : "text",
  "display_width" : null,
  "label" : "Text",
  "required" : true,
  "locked" : false,
  "validation_regex" : "",
  "placeholder" : "Grow your savings with a high-yield cash account.",
  "allow_new_line" : false,
  "show_emoji_picker" : false,
  "type" : "text",
  "default" : "Default text"
}, {
  "id" : "258311dc-7cb1-0b72-3b94-c3fb148037be",
  "name" : "description",
  "display_width" : null,
  "label" : "Description",
  "required" : false,
  "locked" : false,
  "validation_regex" : "",
  "placeholder" : "For teams that need additional security, control, and support.",
  "allow_new_line" : false,
  "show_emoji_picker" : false,
  "type" : "text"
}, {
  "id" : "4b194f81-9e02-b64b-3404-14a06fc0f5ab",
  "name" : "price",
  "display_width" : null,
  "label" : "Price",
  "required" : false,
  "locked" : false,
  "display" : "text",
  "step" : 1,
  "type" : "number",
  "default" : 0
}, {
  "id" : "969ea624-0b65-5082-1748-4c6469e29454",
  "name" : "price_frequency",
  "display_width" : null,
  "label" : "Price Frequency",
  "required" : false,
  "locked" : false,
  "validation_regex" : "",
  "allow_new_line" : false,
  "show_emoji_picker" : false,
  "type" : "text",
  "default" : "per month"
}, {
  "id" : "88b71508-e766-1ad3-142c-883a03f9cc1d",
  "name" : "features",
  "display_width" : null,
  "label" : "Features",
  "required" : false,
  "locked" : false,
  "occurrence" : {
    "min" : 0,
    "max" : 4,
    "sorting_label_field" : null,
    "default" : 4
  },
  "type" : "richtext"
}, {
  "id" : "button_text",
  "name" : "button_text",
  "display_width" : null,
  "label" : "Button text",
  "required" : false,
  "locked" : false,
  "validation_regex" : "",
  "allow_new_line" : false,
  "show_emoji_picker" : false,
  "type" : "text",
  "default" : "Sign up for free"
}, {
  "id" : "button_link",
  "name" : "button_link",
  "display_width" : null,
  "label" : "Button link",
  "required" : false,
  "locked" : false,
  "supported_types" : [ ],
  "show_advanced_rel_options" : false,
  "type" : "link",
  "default" : {
    "url" : {
      "content_id" : null,
      "type" : "EXTERNAL",
      "href" : ""
    }
  }
}, {
  "id" : "styles",
  "name" : "styles",
  "display_width" : null,
  "label" : "Styles",
  "required" : false,
  "locked" : false,
  "children" : [ {
    "id" : "styles.features",
    "name" : "features",
    "display_width" : null,
    "label" : "Features",
    "required" : false,
    "locked" : false,
    "children" : [ {
      "id" : "styles.features.icon",
      "name" : "icon",
      "display_width" : null,
      "label" : "Icon",
      "required" : false,
      "locked" : false,
      "children" : [ {
        "id" : "styles.features.icon.color",
        "name" : "color",
        "display_width" : null,
        "label" : "Color",
        "required" : false,
        "locked" : false,
        "visibility" : {
          "controlling_field" : null,
          "controlling_field_path" : null,
          "controlling_value_regex" : null,
          "property" : null,
          "operator" : null,
          "access" : null,
          "hidden_subfields" : {
            "opacity" : true
          }
        },
        "type" : "color",
        "default" : {
          "color" : null,
          "opacity" : null,
          "rgba" : null,
          "rgb" : null,
          "hex" : null
        }
      } ],
      "tab" : "STYLE",
      "expanded" : false,
      "group_occurrence_meta" : null,
      "type" : "group",
      "default" : {
        "color" : {
          "color" : null,
          "opacity" : null,
          "rgba" : null,
          "rgb" : null,
          "hex" : null
        }
      }
    }, {
      "id" : "styles.features.text",
      "name" : "text",
      "display_width" : null,
      "label" : "Text",
      "required" : false,
      "locked" : false,
      "children" : [ {
        "id" : "styles.features.text.font",
        "name" : "font",
        "display_width" : null,
        "label" : "Font",
        "required" : false,
        "locked" : false,
        "load_external_fonts" : true,
        "type" : "font",
        "default" : {
          "font" : null,
          "font_set" : "DEFAULT",
          "styles" : null,
          "size" : null,
          "size_unit" : null,
          "color" : null,
          "variant" : null,
          "fallback" : null,
          "style" : null
        }
      } ],
      "tab" : "STYLE",
      "expanded" : false,
      "group_occurrence_meta" : null,
      "type" : "group",
      "default" : {
        "font" : {
          "font" : null,
          "font_set" : "DEFAULT",
          "styles" : null,
          "size" : null,
          "size_unit" : null,
          "color" : null,
          "variant" : null,
          "fallback" : null,
          "style" : null
        }
      }
    }, {
      "id" : "styles.features.border",
      "name" : "border",
      "display_width" : null,
      "label" : "Border",
      "required" : false,
      "locked" : false,
      "children" : [ {
        "id" : "styles.features.border.color",
        "name" : "color",
        "display_width" : null,
        "label" : "Color",
        "required" : false,
        "locked" : false,
        "type" : "color",
        "default" : {
          "color" : null,
          "opacity" : null,
          "rgba" : null,
          "rgb" : null,
          "hex" : null
        }
      } ],
      "tab" : "STYLE",
      "expanded" : false,
      "group_occurrence_meta" : null,
      "type" : "group",
      "default" : {
        "color" : {
          "color" : null,
          "opacity" : null,
          "rgba" : null,
          "rgb" : null,
          "hex" : null
        }
      }
    }, {
      "id" : "styles.features.alignment",
      "name" : "alignment",
      "display_width" : null,
      "label" : "Alignment",
      "required" : false,
      "locked" : false,
      "children" : [ {
        "id" : "styles.features.alignment.alignment",
        "name" : "alignment",
        "display_width" : null,
        "label" : "Alignment",
        "required" : false,
        "locked" : false,
        "alignment_direction" : "HORIZONTAL",
        "type" : "alignment",
        "default" : { }
      } ],
      "tab" : "STYLE",
      "expanded" : false,
      "group_occurrence_meta" : null,
      "type" : "group",
      "default" : {
        "alignment" : { }
      }
    } ],
    "tab" : "STYLE",
    "expanded" : false,
    "group_occurrence_meta" : null,
    "type" : "group",
    "default" : {
      "icon" : {
        "color" : {
          "color" : null,
          "opacity" : null,
          "rgba" : null,
          "rgb" : null,
          "hex" : null
        }
      },
      "text" : {
        "font" : {
          "font" : null,
          "font_set" : "DEFAULT",
          "styles" : null,
          "size" : null,
          "size_unit" : null,
          "color" : null,
          "variant" : null,
          "fallback" : null,
          "style" : null
        }
      },
      "border" : {
        "color" : {
          "color" : null,
          "opacity" : null,
          "rgba" : null,
          "rgb" : null,
          "hex" : null
        }
      },
      "alignment" : {
        "alignment" : { }
      }
    }
  }, {
    "id" : "styles.price",
    "name" : "price",
    "display_width" : null,
    "label" : "Price",
    "required" : false,
    "locked" : false,
    "children" : [ {
      "id" : "styles.price.text",
      "name" : "text",
      "display_width" : null,
      "label" : "Text",
      "required" : false,
      "locked" : false,
      "children" : [ {
        "id" : "styles.price.text.font",
        "name" : "font",
        "display_width" : null,
        "label" : "Font",
        "required" : false,
        "locked" : false,
        "load_external_fonts" : true,
        "type" : "font",
        "default" : {
          "font" : null,
          "font_set" : "DEFAULT",
          "styles" : null,
          "size" : null,
          "size_unit" : null,
          "color" : null,
          "variant" : null,
          "fallback" : null,
          "style" : null
        }
      } ],
      "tab" : "STYLE",
      "expanded" : false,
      "group_occurrence_meta" : null,
      "type" : "group",
      "default" : {
        "font" : {
          "font" : null,
          "font_set" : "DEFAULT",
          "styles" : null,
          "size" : null,
          "size_unit" : null,
          "color" : null,
          "variant" : null,
          "fallback" : null,
          "style" : null
        }
      }
    }, {
      "id" : "styles.price.alignment",
      "name" : "alignment",
      "display_width" : null,
      "label" : "Alignment",
      "required" : false,
      "locked" : false,
      "children" : [ {
        "id" : "styles.price.alignment.alignment",
        "name" : "alignment",
        "display_width" : null,
        "label" : "Alignment",
        "required" : false,
        "locked" : false,
        "alignment_direction" : "HORIZONTAL",
        "type" : "alignment",
        "default" : { }
      } ],
      "tab" : "STYLE",
      "expanded" : false,
      "group_occurrence_meta" : null,
      "type" : "group",
      "default" : {
        "alignment" : { }
      }
    } ],
    "tab" : "STYLE",
    "expanded" : false,
    "group_occurrence_meta" : null,
    "type" : "group",
    "default" : {
      "text" : {
        "font" : {
          "font" : null,
          "font_set" : "DEFAULT",
          "styles" : null,
          "size" : null,
          "size_unit" : null,
          "color" : null,
          "variant" : null,
          "fallback" : null,
          "style" : null
        }
      },
      "alignment" : {
        "alignment" : { }
      }
    }
  }, {
    "id" : "styles.button",
    "name" : "button",
    "display_width" : null,
    "label" : "Button",
    "required" : false,
    "locked" : false,
    "children" : [ {
      "id" : "styles.button.text",
      "name" : "text",
      "display_width" : null,
      "label" : "Text",
      "required" : false,
      "locked" : false,
      "children" : [ {
        "id" : "styles.button.text.font",
        "name" : "font",
        "display_width" : null,
        "label" : "Font",
        "required" : false,
        "locked" : false,
        "load_external_fonts" : true,
        "type" : "font",
        "default" : {
          "font" : null,
          "font_set" : "DEFAULT",
          "styles" : null,
          "size" : null,
          "size_unit" : null,
          "color" : null,
          "variant" : null,
          "fallback" : null,
          "style" : null
        }
      } ],
      "tab" : "STYLE",
      "expanded" : false,
      "group_occurrence_meta" : null,
      "type" : "group",
      "default" : {
        "font" : {
          "font" : null,
          "font_set" : "DEFAULT",
          "styles" : null,
          "size" : null,
          "size_unit" : null,
          "color" : null,
          "variant" : null,
          "fallback" : null,
          "style" : null
        }
      }
    }, {
      "id" : "styles.button.background",
      "name" : "background",
      "display_width" : null,
      "label" : "Background",
      "required" : false,
      "locked" : false,
      "children" : [ {
        "id" : "styles.button.background.color",
        "name" : "color",
        "display_width" : null,
        "label" : "Color",
        "required" : false,
        "locked" : false,
        "type" : "color",
        "default" : {
          "color" : null,
          "opacity" : null,
          "rgba" : null,
          "rgb" : null,
          "hex" : null
        }
      } ],
      "tab" : "STYLE",
      "expanded" : false,
      "group_occurrence_meta" : null,
      "type" : "group",
      "default" : {
        "color" : {
          "color" : null,
          "opacity" : null,
          "rgba" : null,
          "rgb" : null,
          "hex" : null
        }
      }
    }, {
      "id" : "styles.button.border",
      "name" : "border",
      "display_width" : null,
      "label" : "Border",
      "required" : false,
      "locked" : false,
      "children" : [ {
        "id" : "styles.button.border.border",
        "name" : "border",
        "display_width" : null,
        "label" : "Border",
        "required" : false,
        "locked" : false,
        "allow_custom_border_sides" : false,
        "type" : "border",
        "default" : { }
      } ],
      "tab" : "STYLE",
      "expanded" : false,
      "group_occurrence_meta" : null,
      "type" : "group",
      "default" : {
        "border" : { }
      }
    }, {
      "id" : "styles.button.corner",
      "name" : "corner",
      "display_width" : null,
      "label" : "Corner",
      "required" : false,
      "locked" : false,
      "children" : [ {
        "id" : "styles.button.corner.radius",
        "name" : "radius",
        "display_width" : null,
        "label" : "Radius",
        "required" : false,
        "locked" : false,
        "display" : "text",
        "max" : 100,
        "step" : 1,
        "suffix" : "px",
        "type" : "number"
      } ],
      "tab" : "STYLE",
      "expanded" : false,
      "group_occurrence_meta" : null,
      "type" : "group",
      "default" : { }
    }, {
      "id" : "styles.button.spacing",
      "name" : "spacing",
      "display_width" : null,
      "label" : "Spacing",
      "required" : false,
      "locked" : false,
      "children" : [ {
        "id" : "styles.button.spacing.spacing",
        "name" : "spacing",
        "display_width" : null,
        "label" : "Spacing",
        "required" : false,
        "locked" : false,
        "visibility" : {
          "controlling_field" : null,
          "controlling_field_path" : null,
          "controlling_value_regex" : null,
          "property" : null,
          "operator" : null,
          "access" : null,
          "hidden_subfields" : {
            "margin" : true
          }
        },
        "type" : "spacing",
        "default" : { }
      } ],
      "tab" : "STYLE",
      "expanded" : false,
      "group_occurrence_meta" : null,
      "type" : "group",
      "default" : {
        "spacing" : { }
      }
    }, {
      "id" : "styles.button.alignment",
      "name" : "alignment",
      "display_width" : null,
      "label" : "Alignment",
      "required" : false,
      "locked" : false,
      "children" : [ {
        "id" : "styles.button.alignment.alignment",
        "name" : "alignment",
        "display_width" : null,
        "label" : "Alignment",
        "required" : false,
        "locked" : false,
        "alignment_direction" : "HORIZONTAL",
        "type" : "alignment",
        "default" : { }
      } ],
      "tab" : "STYLE",
      "expanded" : false,
      "group_occurrence_meta" : null,
      "type" : "group",
      "default" : {
        "alignment" : { }
      }
    } ],
    "tab" : "STYLE",
    "expanded" : false,
    "group_occurrence_meta" : null,
    "type" : "group",
    "default" : {
      "text" : {
        "font" : {
          "font" : null,
          "font_set" : "DEFAULT",
          "styles" : null,
          "size" : null,
          "size_unit" : null,
          "color" : null,
          "variant" : null,
          "fallback" : null,
          "style" : null
        }
      },
      "background" : {
        "color" : {
          "color" : null,
          "opacity" : null,
          "rgba" : null,
          "rgb" : null,
          "hex" : null
        }
      },
      "border" : {
        "border" : { }
      },
      "corner" : { },
      "spacing" : {
        "spacing" : { }
      },
      "alignment" : {
        "alignment" : { }
      }
    }
  }, {
    "id" : "styles.card",
    "name" : "card",
    "display_width" : null,
    "label" : "Card",
    "required" : false,
    "locked" : false,
    "children" : [ {
      "id" : "styles.card.background",
      "name" : "background",
      "display_width" : null,
      "label" : "Background",
      "required" : false,
      "locked" : false,
      "children" : [ {
        "id" : "styles.card.background.background_type",
        "name" : "background_type",
        "display_width" : null,
        "label" : "Background type",
        "required" : false,
        "locked" : false,
        "display" : "radio",
        "choices" : [ [ "none", "None" ], [ "color", "Background color" ], [ "gradient", "Background gradient" ], [ "image", "Background image" ] ],
        "multiple" : false,
        "reordering_enabled" : true,
        "preset" : null,
        "type" : "choice",
        "default" : "none"
      }, {
        "id" : "styles.card.background.color",
        "name" : "color",
        "display_width" : null,
        "label" : "Color",
        "required" : false,
        "locked" : false,
        "visibility" : {
          "controlling_field" : "styles.card.background.background_type",
          "controlling_field_path" : null,
          "controlling_value_regex" : "color",
          "property" : null,
          "operator" : "EQUAL",
          "access" : null
        },
        "type" : "color",
        "default" : {
          "color" : null,
          "opacity" : null,
          "rgba" : null,
          "rgb" : null,
          "hex" : null
        }
      }, {
        "id" : "styles.card.background.gradient",
        "name" : "gradient",
        "display_width" : null,
        "label" : "Gradient",
        "required" : false,
        "locked" : false,
        "visibility" : {
          "controlling_field" : "styles.card.background.background_type",
          "controlling_field_path" : null,
          "controlling_value_regex" : "gradient",
          "property" : null,
          "operator" : "EQUAL",
          "access" : null
        },
        "type" : "gradient",
        "default" : { }
      }, {
        "id" : "styles.card.background.image",
        "name" : "image",
        "display_width" : null,
        "label" : "Image",
        "required" : false,
        "locked" : false,
        "visibility" : {
          "controlling_field" : "styles.card.background.background_type",
          "controlling_field_path" : null,
          "controlling_value_regex" : "image",
          "property" : null,
          "operator" : "EQUAL",
          "access" : null
        },
        "type" : "backgroundimage",
        "default" : {
          "src" : "",
          "background_position" : "MIDDLE_CENTER",
          "background_size" : "cover"
        }
      } ],
      "tab" : "STYLE",
      "expanded" : false,
      "group_occurrence_meta" : null,
      "type" : "group",
      "default" : {
        "background_type" : "none",
        "color" : {
          "color" : null,
          "opacity" : null,
          "rgba" : null,
          "rgb" : null,
          "hex" : null
        },
        "gradient" : { },
        "image" : {
          "src" : "",
          "background_position" : "MIDDLE_CENTER",
          "background_size" : "cover"
        }
      }
    }, {
      "id" : "styles.card.border",
      "name" : "border",
      "display_width" : null,
      "label" : "Border",
      "required" : false,
      "locked" : false,
      "children" : [ {
        "id" : "styles.card.border.border",
        "name" : "border",
        "display_width" : null,
        "label" : "Border",
        "required" : false,
        "locked" : false,
        "allow_custom_border_sides" : false,
        "type" : "border",
        "default" : { }
      } ],
      "tab" : "STYLE",
      "expanded" : false,
      "group_occurrence_meta" : null,
      "type" : "group",
      "default" : {
        "border" : { }
      }
    }, {
      "id" : "styles.card.corner",
      "name" : "corner",
      "display_width" : null,
      "label" : "Corner",
      "required" : false,
      "locked" : false,
      "children" : [ {
        "id" : "styles.card.corner.radius",
        "name" : "radius",
        "display_width" : null,
        "label" : "Radius",
        "required" : false,
        "locked" : false,
        "display" : "text",
        "max" : 100,
        "step" : 1,
        "suffix" : "px",
        "type" : "number"
      } ],
      "tab" : "STYLE",
      "expanded" : false,
      "group_occurrence_meta" : null,
      "type" : "group",
      "default" : { }
    }, {
      "id" : "styles.card.spacing",
      "name" : "spacing",
      "display_width" : null,
      "label" : "Spacing",
      "required" : false,
      "locked" : false,
      "children" : [ {
        "id" : "styles.card.spacing.spacing",
        "name" : "spacing",
        "display_width" : null,
        "label" : "Spacing",
        "required" : false,
        "locked" : false,
        "type" : "spacing",
        "default" : { }
      } ],
      "tab" : "STYLE",
      "expanded" : false,
      "group_occurrence_meta" : null,
      "type" : "group",
      "default" : {
        "spacing" : { }
      }
    } ],
    "tab" : "STYLE",
    "expanded" : false,
    "group_occurrence_meta" : null,
    "type" : "group",
    "default" : {
      "background" : {
        "background_type" : "none",
        "color" : {
          "color" : null,
          "opacity" : null,
          "rgba" : null,
          "rgb" : null,
          "hex" : null
        },
        "gradient" : { },
        "image" : {
          "src" : "",
          "background_position" : "MIDDLE_CENTER",
          "background_size" : "cover"
        }
      },
      "border" : {
        "border" : { }
      },
      "corner" : { },
      "spacing" : {
        "spacing" : { }
      }
    }
  } ],
  "tab" : "STYLE",
  "expanded" : false,
  "group_occurrence_meta" : null,
  "type" : "group",
  "default" : {
    "features" : {
      "icon" : {
        "color" : {
          "color" : null,
          "opacity" : null,
          "rgba" : null,
          "rgb" : null,
          "hex" : null
        }
      },
      "text" : {
        "font" : {
          "font" : null,
          "font_set" : "DEFAULT",
          "styles" : null,
          "size" : null,
          "size_unit" : null,
          "color" : null,
          "variant" : null,
          "fallback" : null,
          "style" : null
        }
      },
      "border" : {
        "color" : {
          "color" : null,
          "opacity" : null,
          "rgba" : null,
          "rgb" : null,
          "hex" : null
        }
      },
      "alignment" : {
        "alignment" : { }
      }
    },
    "price" : {
      "text" : {
        "font" : {
          "font" : null,
          "font_set" : "DEFAULT",
          "styles" : null,
          "size" : null,
          "size_unit" : null,
          "color" : null,
          "variant" : null,
          "fallback" : null,
          "style" : null
        }
      },
      "alignment" : {
        "alignment" : { }
      }
    },
    "button" : {
      "text" : {
        "font" : {
          "font" : null,
          "font_set" : "DEFAULT",
          "styles" : null,
          "size" : null,
          "size_unit" : null,
          "color" : null,
          "variant" : null,
          "fallback" : null,
          "style" : null
        }
      },
      "background" : {
        "color" : {
          "color" : null,
          "opacity" : null,
          "rgba" : null,
          "rgb" : null,
          "hex" : null
        }
      },
      "border" : {
        "border" : { }
      },
      "corner" : { },
      "spacing" : {
        "spacing" : { }
      },
      "alignment" : {
        "alignment" : { }
      }
    },
    "card" : {
      "background" : {
        "background_type" : "none",
        "color" : {
          "color" : null,
          "opacity" : null,
          "rgba" : null,
          "rgb" : null,
          "hex" : null
        },
        "gradient" : { },
        "image" : {
          "src" : "",
          "background_position" : "MIDDLE_CENTER",
          "background_size" : "cover"
        }
      },
      "border" : {
        "border" : { }
      },
      "corner" : { },
      "spacing" : {
        "spacing" : { }
      }
    }
  }
}, {
  "id" : "931183c2-c9c6-1ab7-aec9-3adc10b161c6",
  "name" : "footnote",
  "display_width" : null,
  "label" : "Footnote",
  "help_text" : "Optional",
  "required" : false,
  "locked" : false,
  "validation_regex" : "",
  "allow_new_line" : false,
  "show_emoji_picker" : false,
  "type" : "text"
} ]